LICENSE
MANIFEST.in
README.md
setup.cfg
setup.py
versioneer.py
molpy/.DS_Store
molpy/__init__.py
molpy/_version.py
molpy/cli.py
molpy/molpy.py
molpy/util.py
molpy/data/.DS_Store
molpy/data/1bna.xyz
molpy/data/README.md
molpy/data/__init__.py
molpy/data/benzene.xyz
molpy/data/look_and_say.dat
molpy/data/read_xyz_files.py
molpy/data/reader.py
molpy/data/water.xyz
molpy/tests/__init__.py
molpy/tests/test_molpy.py
molpy/tests/test_read_xyz_files.py
molpy/tests/test_util.py
molpy_demo.egg-info/PKG-INFO
molpy_demo.egg-info/SOURCES.txt
molpy_demo.egg-info/dependency_links.txt
molpy_demo.egg-info/entry_points.txt
molpy_demo.egg-info/top_level.txt