Metadata-Version: 2.1
Name: molpy-demo
Version: 0.1.1
Summary: UNKNOWN
Home-page: UNKNOWN
Author: Yonghui Chen
Author-email: cpuyonghui@gmail.com
License: MIT
Platform: UNKNOWN
